Metadata-Version: 2.1
Name: synchronizer
Version: 2.0.2
Summary: A collection of utilities for CGI-VFX to copy files from one place to another, find out basic stat differences between them and handle file sequences and textures (tx files).
Home-page: https://github.com/xiancg/synchronizer
Author: Chris Granados - Xian
Author-email: info@chrisgranados.com
License: UNKNOWN
Download-URL: https://github.com/xiancg/synchronizer/archive/v2.0.2.tar.gz
Platform: UNKNOWN
Classifier: Development Status :: 5 - Production/Stable
Classifier: Intended Audience :: Developers
Classifier: Programming Language :: Python :: 2.7
Classifier: Programming Language :: Python :: 3.7
Requires-Python: >=2.7, !=3.0.*, !=3.1.*, !=3.2.*, !=3.3.*, !=3.4.*, <4
Provides-Extra: dev
Provides-Extra: docs
